cosy1.libs/libgssapi_krb5-497db0c6.so.2.2
cosy1.libs/libquadmath-96973f99.so.0.0.0
cosy1.libs/libsqlite3-f79e2a86.so.0.8.6
cosy1.libs/libselinux-0922c95c.so.1
cosy1.libs/libpcre-9513aab5.so.1.2.0
cosy1.libs/libkeyutils-dfe70bd6.so.1.5
cosy1.libs/libproj-24128ac9.so.25.9.3.0
cosy1.libs/libcom_err-2abe824b.so.2.1
cosy1.libs/libk5crypto-b1f99d5c.so.3.1
cosy1.libs/liblapack-1ad85175.so.3.4.2
cosy1.libs/libkrb5-fcafa220.so.3.3
cosy1.libs/libkrb5support-d0bcff84.so.0.1
cosy1.libs/libssl-cd1d6220.so.1.0.2k
cosy1.libs/libcrypto-d3570994.so.1.0.2k
cosy1.libs/libjbig-78348776.so.2.0
cosy1.libs/libjpeg-43436dd5.so.62.1.0
cosy1.libs/libtiff-b6eb22fb.so.5.2.0
cosy1.libs/libgfortran-91cc3cb1.so.3.0.0
cosy1.libs/libblas-357956a1.so.3.4.2
cosy/backend.cpython-39-x86_64-linux-gnu.so
cosy/geo.py
cosy/util.py
cosy/__init__.py
cosy/affine.py
cosy/proj_data/nad.lst
cosy/proj_data/proj.db
cosy/proj_data/ITRF2008
cosy/proj_data/nad27
cosy/proj_data/projjson.schema.json
cosy/proj_data/nad83
cosy/proj_data/other.extra
cosy/proj_data/ITRF2014
cosy/proj_data/proj.ini
cosy/proj_data/CH
cosy/proj_data/ITRF2000
cosy/proj_data/GL27
cosy/proj_data/world
cosy/proj_data/triangulation.schema.json
cosy/proj_data/deformation_model.schema.json
cosy1-0.1.2.dist-info/LICENSE
cosy1-0.1.2.dist-info/RECORD
cosy1-0.1.2.dist-info/top_level.txt
cosy1-0.1.2.dist-info/WHEEL
cosy1-0.1.2.dist-info/METADATA
